pytest_skippy/__init__.py
pytest_skippy/_version.py
pytest_skippy/core.py
pytest_skippy/git.py
pytest_skippy/imp.py
pytest_skippy/parse.py
pytest_skippy/plugin.py
pytest_skippy/util.py
pytest_skippy-0.1.1.dist-info/DESCRIPTION.rst
pytest_skippy-0.1.1.dist-info/LICENSE.txt
pytest_skippy-0.1.1.dist-info/METADATA
pytest_skippy-0.1.1.dist-info/RECORD
pytest_skippy-0.1.1.dist-info/WHEEL
pytest_skippy-0.1.1.dist-info/entry_points.txt
pytest_skippy-0.1.1.dist-info/metadata.json
pytest_skippy-0.1.1.dist-info/top_level.txt
