Metadata-Version: 2.0
Name: pytest-skippy
Version: 0.1.1
Summary: Automatically skip tests that don't need to run!
Home-page: https://github.com/a-feld/pytest-skippy
Author: Allan Feldman
Author-email: allan.d.feldman@gmail.com
License: MIT
Keywords: pytest incremental testing
Platform: UNKNOWN
Classifier: Development Status :: 3 - Alpha
Classifier: Intended Audience :: Developers
Classifier: Topic :: Software Development :: Testing
Classifier: Framework :: Pytest
Classifier: License :: OSI Approved :: MIT License
Classifier: Programming Language :: Python :: 2
Classifier: Programming Language :: Python :: 2.7
Classifier: Programming Language :: Python :: 3
Classifier: Programming Language :: Python :: 3.4
Classifier: Programming Language :: Python :: 3.5
Classifier: Programming Language :: Python :: 3.6
Classifier: Environment :: Console
Requires-Dist: pytest (>=2.3.4)
Requires-Dist: stdlib-list (>=0.4.0)
Provides-Extra: dev
Requires-Dist: tox; extra == 'dev'
Requires-Dist: pytest; extra == 'dev'
Requires-Dist: pytest-git; extra == 'dev'
Requires-Dist: flake8; extra == 'dev'
Requires-Dist: coverage; extra == 'dev'
Requires-Dist: gitpython; extra == 'dev'
Requires-Dist: sphinx; extra == 'dev'
Requires-Dist: sphinx-rtd-theme; extra == 'dev'
